tweepy_parrot/__init__.py
tweepy_parrot/bot.py
tweepy_parrot/data.py
tweepy_parrot/listener.py
tweepy_parrot/models.py
tweepy_parrot/parrots.py
tweepy_parrot/settings.py
tweepy_parrot-0.0.3.dist-info/LICENSE.md
tweepy_parrot-0.0.3.dist-info/METADATA
tweepy_parrot-0.0.3.dist-info/WHEEL
tweepy_parrot-0.0.3.dist-info/top_level.txt
tweepy_parrot-0.0.3.dist-info/RECORD
