Metadata-Version: 2.1
Name: tweepy-parrot
Version: 0.0.3
Summary: A library built on top of Tweepy for making Twitter bots
Home-page: https://github.com/MetaBytez/tweepy_parrot
Author: Will Johns
Author-email: will@wcj.dev
License: UNKNOWN
Platform: UNKNOWN
Classifier: Programming Language :: Python :: 3
Classifier: License :: OSI Approved :: MIT License
Classifier: Operating System :: OS Independent
Requires-Python: >=3.6
Requires-Dist: tweepy
Requires-Dist: pydantic
Requires-Dist: python-dotenv
